contextifyai/__init__.py
contextifyai/config.py
contextifyai/vercel_compatible.py
contextifyai-0.1.3.dist-info/METADATA
contextifyai-0.1.3.dist-info/WHEEL
contextifyai-0.1.3.dist-info/top_level.txt
contextifyai-0.1.3.dist-info/RECORD
