Metadata-Version: 2.4
Name: contextifyai
Version: 0.1.3
Summary: The simplest way to build AI agents - Built on Vercel AI SDK with PromptFlow tracking
Author-email: ContextifyAI <hello@contextifyai.dev>
License: MIT
Project-URL: Homepage, https://github.com/sanjevvishnu/contextifyAI
Project-URL: Documentation, https://github.com/sanjevvishnu/contextifyAI#readme
Project-URL: Repository, https://github.com/sanjevvishnu/contextifyAI
Project-URL: Issues, https://github.com/sanjevvishnu/contextifyAI/issues
Keywords: ai,agentic-ai,llm,openai,anthropic,vercel-ai-sdk,promptflow,tracking,context-management
Classifier: Development Status :: 3 - Alpha
Classifier: Intended Audience :: Developers
Classifier: License :: OSI Approved :: MIT License
Classifier: Programming Language :: Python :: 3
Classifier: Programming Language :: Python :: 3.8
Classifier: Programming Language :: Python :: 3.9
Classifier: Programming Language :: Python :: 3.10
Classifier: Programming Language :: Python :: 3.11
Classifier: Programming Language :: Python :: 3.12
Classifier: Topic :: Software Development :: Libraries :: Python Modules
Classifier: Topic :: Scientific/Engineering :: Artificial Intelligence
Requires-Python: >=3.8
Requires-Dist: ai-sdk-python>=0.1.0
Requires-Dist: requests>=2.31.0
Requires-Dist: python-dotenv>=1.0.0
Provides-Extra: dev
Requires-Dist: pytest>=7.0.0; extra == "dev"
Requires-Dist: black>=23.0.0; extra == "dev"
Requires-Dist: mypy>=1.0.0; extra == "dev"
Requires-Dist: ruff>=0.1.0; extra == "dev"
